Metadata-Version: 2.1
Name: simpleocr
Version: 0.0.16
Summary: A ocr tool for traditional chinese
Home-page: https://github.com/xianyuntang/simpleocr
Author: xt1800i
Author-email: xt1800i@gmail.com
License: UNKNOWN
Platform: UNKNOWN
Classifier: Programming Language :: Python :: 3
Classifier: License :: OSI Approved :: Apache Software License
Classifier: Operating System :: OS Independent
Requires-Python: >=3.6
